streaming_deep_rl/__init__.py
streaming_deep_rl/streaming_deep_rl.py
streaming_deep_rl-0.0.2.dist-info/METADATA
streaming_deep_rl-0.0.2.dist-info/WHEEL
streaming_deep_rl-0.0.2.dist-info/licenses/LICENSE
streaming_deep_rl-0.0.2.dist-info/RECORD
