Metadata-Version: 2.3
Name: streaming-deep-rl
Version: 0.0.2
Summary: Streaming Deep Reinforcement Learning
Project-URL: Homepage, https://pypi.org/project/streaming-deep-rl/
Project-URL: Repository, https://github.com/lucidrains/streaming-deep-rl
Author-email: Phil Wang <lucidrains@gmail.com>
License: MIT License
Keywords: artificial intelligence,deep learning,reinforcement learning,streaming
Classifier: Development Status :: 4 - Beta
Classifier: Intended Audience :: Developers
Classifier: License :: OSI Approved :: MIT License
Classifier: Programming Language :: Python :: 3.9
Classifier: Topic :: Scientific/Engineering :: Artificial Intelligence
Requires-Python: >=3.9
Requires-Dist: adam-atan2-pytorch>=0.1.1
Requires-Dist: einops>=0.8.0
Requires-Dist: gymnasium[box2d]>=1.0
Requires-Dist: torch>=2.0
Provides-Extra: examples
Provides-Extra: test
Requires-Dist: pytest; extra == 'test'
